<?xml version="1.0" encoding="UTF-8"?>
<!DOCTYPE configuration PUBLIC "-//mybatis.org//DTD Config 3.0//EN" "http://mybatis.org/dtd/mybatis-3-config.dtd">
<configuration>


<settings>
 <setting name="mapUnderscoreToCamelCase" value="false"/>
</settings>

<typeAliases>
 <typeAlias alias="board" type="com.team2.docgram.dto.BoardDto"/>
 <typeAlias alias="user" type="com.team2.docgram.dto.UserDto"/>
 <typeAlias alias="team" type="com.team2.docgram.dto.TeamDto"/>
 <typeAlias alias="hashtag" type="com.team2.docgram.dto.HashtagDto"/>
 <typeAlias alias="rank" type="com.team2.docgram.dto.RankDto"/>
 <typeAlias alias="dept" type="com.team2.docgram.dto.DepartmentDto"/>
 <typeAlias alias="related" type="com.team2.docgram.dto.RelatedDto"/>
 <typeAlias alias="hashtagTable" type="com.team2.docgram.dto.HashtagTableDto"/>
 <typeAlias alias="file" type="com.team2.docgram.dto.FileDto"/>
</typeAliases>

</configuration>

